coAutomationLib/__init__.py
coAutomationLib/changeOrderAutomation.py
coAutomationLib/test.py
coAutomationLib/test_lib.py
coAutomationLib-1.4.0.dist-info/METADATA
coAutomationLib-1.4.0.dist-info/WHEEL
coAutomationLib-1.4.0.dist-info/top_level.txt
coAutomationLib-1.4.0.dist-info/RECORD
