Metadata-Version: 2.1
Name: coAutomationLib
Version: 1.4.0
Summary: A Python package to create servicenow change order
Home-page: 
Author: 
Author-email: 
License: BSD 2-clause
Requires-Dist: mpi4py >=2.0
Requires-Dist: numpy
